generic_sram_bfms/__init__.py
generic_sram_bfms/generic_sram_byte_en_dualport_target_bfm.py
generic_sram_bfms/generic_sram_byte_en_target_bfm.py
generic_sram_bfms/generic_sram_line_en_initiator_bfm.py
pybfms_generic_sram-0.0.1.20200226.3.dist-info/LICENSE
pybfms_generic_sram-0.0.1.20200226.3.dist-info/METADATA
pybfms_generic_sram-0.0.1.20200226.3.dist-info/WHEEL
pybfms_generic_sram-0.0.1.20200226.3.dist-info/top_level.txt
pybfms_generic_sram-0.0.1.20200226.3.dist-info/RECORD
